shadho/__init__.py
shadho/benchmarks.py
shadho/configuration.py
shadho/hardware.py
shadho/scaling.py
shadho/shadho.py
shadho/spaces.py
shadho/utils.py
shadho/worker.py
shadho/installers/__init__.py
shadho/installers/install_workqueue.sh
shadho/installers/workqueue.py
shadho/managers/__init__.py
shadho/managers/local.py
shadho/managers/manager.py
shadho/managers/manager_factory.py
shadho/managers/workqueue.py
shadho/workers/__init__.py
shadho/workers/workqueue.py
shadho-0.4.5.dist-info/LICENSE
shadho-0.4.5.dist-info/METADATA
shadho-0.4.5.dist-info/WHEEL
shadho-0.4.5.dist-info/top_level.txt
shadho-0.4.5.dist-info/RECORD
