Metadata-Version: 2.1
Name: shadho
Version: 0.4.5
Summary: Hyperparameter optimizer with distributed hardware at heart
Home-page: https://github.com/jeffkinnison/shadho
Author: Jeff Kinnison
Author-email: jkinniso@nd.edu
Keywords: machine_learning hyperparameters distributed_computing
Classifier: Development Status :: 4 - Beta
Classifier: Intended Audience :: Science/Research
Classifier: License :: OSI Approved :: MIT License
Classifier: Topic :: Scientific/Engineering :: Artificial Intelligence
Classifier: Programming Language :: Python :: 3
Classifier: Programming Language :: Python :: 3.5
Classifier: Programming Language :: Python :: 3.6
Classifier: Programming Language :: Python :: 3.7
Classifier: Operating System :: POSIX
Classifier: Operating System :: Unix
Requires-Python: >=3.5
License-File: LICENSE
Requires-Dist: numpy
Requires-Dist: scipy
Requires-Dist: scikit-learn
Requires-Dist: pyrameter
